Metadata-Version: 2.1
Name: kditor
Version: 0.0.2
Summary: A module that helps you to modify yaml file easily.
Author: NickLin
